flask_mde/__init__.py
flask_mde/models.py
flask_mde/static/css/mde.css
flask_mde/static/css/prettify.css
flask_mde/static/images/a.png
flask_mde/static/images/b.png
flask_mde/static/images/classic-buttons.png
flask_mde/static/js/Markdown.Converter.js
flask_mde/static/js/Markdown.Editor.js
flask_mde/static/js/Markdown.Extra.js
flask_mde/static/js/Markdown.Sanitizer.js
flask_mde/static/js/Pagedown-Extra-License.txt
flask_mde/static/js/Pagedown-License.txt
flask_mde/static/js/mde.js
flask_mde/static/js/prettify.js
Flask_MDE-1.2.1.dist-info/LICENSE
Flask_MDE-1.2.1.dist-info/METADATA
Flask_MDE-1.2.1.dist-info/WHEEL
Flask_MDE-1.2.1.dist-info/top_level.txt
Flask_MDE-1.2.1.dist-info/RECORD
