Metadata-Version: 1.2
Name: Flask-MDE
Version: 1.2.1
Summary: Pagedown for Flask
Home-page: https://github.com/bittobennichan/Flask-MDE
Author: Bitto Bennichan
Author-email: bittobennichan@protonmail.com
License: MIT
Project-URL: Documentation, https://flask-mde.readthedocs.io
Project-URL: Source, https://github.com/bittobennichan/Flask-MDE
Platform: any
Classifier: Environment :: Web Environment
Classifier: Framework :: Flask
Classifier: Intended Audience :: Developers
Classifier: License :: OSI Approved :: MIT License
Classifier: Operating System :: OS Independent
Classifier: Programming Language :: Python
Classifier: Programming Language :: Python :: 3
Classifier: Programming Language :: Python :: 3.6
Classifier: Programming Language :: Python :: 3.7
Classifier: Programming Language :: Python :: 3.8
Classifier: Topic :: Internet :: WWW/HTTP :: Dynamic Content
Classifier: Topic :: Software Development :: Libraries :: Python Modules
Requires-Python: >=3.6
